sesameeg/__init__.py
sesameeg/_template.py
sesameeg/_version.py
sesameeg/dipoles.py
sesameeg/emp_pdf.py
sesameeg/particles.py
sesameeg/sesame.py
sesameeg/io/__init__.py
sesameeg/io/io.py
sesameeg/metrics/__init__.py
sesameeg/metrics/metrics.py
sesameeg/mne/__init__.py
sesameeg/mne/mne_utils.py
sesameeg/tests/__init__.py
sesameeg/tests/test_template.py
sesameeg/utils/__init__.py
sesameeg/utils/check.py
sesameeg/utils/smc_utils.py
sesameeg/viz/__init__.py
sesameeg/viz/viz.py
sesameeg-0.0.3.dist-info/licenses/LICENSE
sesameeg-0.0.3.dist-info/METADATA
sesameeg-0.0.3.dist-info/WHEEL
sesameeg-0.0.3.dist-info/top_level.txt
sesameeg-0.0.3.dist-info/RECORD
